omero_ruletagger/__about__.py
omero_ruletagger/__init__.py
omero_ruletagger/__main__.py
omero_ruletagger/compiler.py
omero_ruletagger/getter.py
omero_ruletagger/logic.py
omero_ruletagger/tagger.py
omero_ruletagger-1.0.0.dist-info/METADATA
omero_ruletagger-1.0.0.dist-info/WHEEL
omero_ruletagger-1.0.0.dist-info/licenses/LICENSE.txt
omero_ruletagger-1.0.0.dist-info/RECORD
