Metadata-Version: 2.4
Name: omero-ruletagger
Version: 1.0.0
Summary: Define rules that create tags in an omero server.
Project-URL: Documentation, https://github.com/LavLabInfrastructure/omero-ruletagger#readme
Project-URL: Issues, https://github.com/LavLabInfrastructure/omero-ruletagger/issues
Project-URL: Source, https://github.com/LavLabInfrastructure/omero-ruletagger
Author-email: barrettMCW <mjbarrett@mcw.edu>
License-Expression: MIT
License-File: LICENSE.txt
Classifier: Programming Language :: Python
Classifier: Programming Language :: Python :: 3.8
Classifier: Programming Language :: Python :: 3.9
Classifier: Programming Language :: Python :: 3.10
Classifier: Programming Language :: Python :: 3.11
Classifier: Programming Language :: Python :: 3.12
Requires-Python: >=3.8
Requires-Dist: inflect
Requires-Dist: omero-py
Requires-Dist: pyyaml
